shared_db/__init__.py
shared_db/database.py
shared_db/models/__init__.py
shared_db/models/auth.py
shared_db/models/base.py
shared_db/models/public.py
shared_db-0.1.11.dist-info/METADATA
shared_db-0.1.11.dist-info/WHEEL
shared_db-0.1.11.dist-info/top_level.txt
shared_db-0.1.11.dist-info/RECORD
