Metadata-Version: 2.2
Name: shared-db
Version: 0.1.11
Summary: The shared database for AgentOS
Author: AgentOS
Requires-Dist: sqlalchemy>=2.0.0
Requires-Dist: pydantic>=2.0.0
Requires-Dist: alembic>=1.14.0
Requires-Dist: python-dotenv>=1.0.0
Requires-Dist: psycopg2-binary>=2.9.0
Dynamic: author
Dynamic: requires-dist
Dynamic: summary
